win_magnification/__init__.py
win_magnification/_functional_wrapper.py
win_magnification/_object_utils.py
win_magnification/_objects.py
win_magnification/_utils.py
win_magnification/_wrapper.py
win_magnification/const.py
win_magnification/effects.py
win_magnification/old.py
win_magnification/tools.py
win_magnification/types.py
WinMagnification-0.1.0.dist-info/LICENSE.md
WinMagnification-0.1.0.dist-info/METADATA
WinMagnification-0.1.0.dist-info/WHEEL
WinMagnification-0.1.0.dist-info/top_level.txt
WinMagnification-0.1.0.dist-info/RECORD
