Metadata-Version: 2.1
Name: WinMagnification
Version: 0.1.0
Summary: Python wrapper for Windows Magnification API
Author: MaxBQb
License: MIT License        
Project-URL: Homepage, https://github.com/MaxBQb/WinMagnification
Project-URL: Bug Tracker, https://github.com/MaxBQb/WinMagnification/issues
Project-URL: Documentation, https://winmagnification.readthedocs.io/en/latest/
Classifier: Programming Language :: Python :: 3
Classifier: License :: OSI Approved :: MIT License
Classifier: Development Status :: 4 - Beta
Classifier: Intended Audience :: Developers
Classifier: Natural Language :: English
Classifier: Programming Language :: Python :: Implementation :: CPython
Classifier: Topic :: Software Development :: Libraries :: Python Modules
Classifier: Operating System :: Microsoft :: Windows :: Windows 10
Requires-Python: >=3.8
License-File: LICENSE.md
